{"stem":"afraid","instances":[{"docId":"amp-transcript__0028","docUri":"amp-transcript__0028.html","score":2,"contexts":[{"form":"afraid","weight":"1","pos":638,"context":"...emigrate before I return in April, when I´m <mark>afraid<\/mark> there will not be room for them? 4) I´m...","fid":"reading-paginate-13"},{"form":"afraid","weight":"1","pos":1187,"context":"...stood outside his door in the early morning, <mark>afraid<\/mark> to go in.\" This was later. Now, Auden was...","fid":"reading-paginate-23"}]},{"docId":"amp-transcript__0009","docUri":"amp-transcript__0009.html","score":1,"contexts":[{"form":"afraid","weight":"1","pos":25,"context":"...emigrate before I return in April , when I'm <mark>afraid<\/mark> there will not be room for them.? 4) I'm...","fid":"reading-paginate-3"}]}]}