{"stem":"attract","instances":[{"docId":"amp-transcript__0033","docUri":"amp-transcript__0033.html","score":1,"contexts":[{"form":"attractive","weight":"1","pos":84,"context":"...Those two volumes by and about Auden sound very <mark>attractive<\/mark>. (Which publisher is interested?) The place to write...","fid":"text-resize-1"}]},{"docId":"amp-transcript__0041","docUri":"amp-transcript__0041.html","score":1,"contexts":[{"form":"attract","weight":"1","pos":37,"context":"...the stories ? A trifle alarmed that it may <mark>attract<\/mark> more torist,which I' sure you don't welcoe any...","fid":"text-resize-3"}]}]}