{"stem":"author","instances":[{"docId":"amp-transcript__0028","docUri":"amp-transcript__0028.html","score":3,"contexts":[{"form":"author","weight":"1","pos":5,"context":"...book calls itself \"a first biography\", and the <mark>author<\/mark> expressly restricts his aims: \"It is not a...","fid":"reading-paginate-3"},{"form":"authorities","weight":"1","pos":900,"context":"...must be left open. The \"Declaration\" to the tax <mark>authorities<\/mark> in which a great poet patiently explains how poetry...","fid":"reading-paginate-17"},{"form":"authorities","weight":"1","pos":1446,"context":" released by the <mark>authorities<\/mark>. In all cases where the cause of death...","fid":"reading-paginate-27"}]}]}