{"stem":"breed","instances":[{"docId":"amp-transcript__0027","docUri":"amp-transcript__0027.html","score":1,"contexts":[{"form":"breeding","weight":"1","pos":553,"context":"...a society could only come into being through selective <mark>breeding<\/mark>, extermination of the physically and mentally unfit...","fid":"reading-paginate-7"}]},{"docId":"amp-transcript__0043","docUri":"amp-transcript__0043.html","score":1,"contexts":[{"form":"breeding","weight":"1","pos":796,"context":"...a society could only come into being through selective <mark>breeding<\/mark>, extermination of the physically and mentally unfit...","fid":"reading-paginate-9"}]}]}