{"stem":"cancel","instances":[{"docId":"amp-transcript__0028","docUri":"amp-transcript__0028.html","score":1,"contexts":[{"form":"cancelled","weight":"1","pos":808,"context":"...area, ample storage space, accessibility, was totally <mark>cancelled<\/mark> out by the permanent clutter. It was a...","fid":"reading-paginate-15"}]},{"docId":"amp-transcript__0042","docUri":"amp-transcript__0042.html","score":1,"contexts":[{"form":"cancel","weight":"1","pos":14,"context":"...thought it was unfair to the kitchen not to <mark>cancel<\/mark>. Have a nice winter and will see you,...","fid":"reading-paginate-3"}]}]}