{"stem":"comment","instances":[{"docId":"amp-transcript__0031","docUri":"amp-transcript__0031.html","score":2,"contexts":[{"form":"comment","weight":"1","pos":89,"context":"...quite recently. Suddenly, Peter bounced me with the <mark>comment<\/mark> that he would \"like an English version as well.\"...","fid":"text-resize-1"},{"form":"comment","weight":"1","pos":299,"context":"...ecumenical service was a novelty here and caused much <mark>comment<\/mark>. How are you and what are you doing...","fid":"text-resize-3"}]},{"docId":"amp-transcript__0028","docUri":"amp-transcript__0028.html","score":1,"contexts":[{"form":"comments","weight":"1","pos":181,"context":"...a starting point, \"Early Auden\"1 which presents and <mark>comments<\/mark> on the poetry, drama and prose up to...","fid":"text-resize-3"}]}]}