{"stem":"diesen","instances":[{"docId":"amp-transcript__0053","docUri":"amp-transcript__0053.html","score":2,"contexts":[{"form":"diesen","weight":"1","pos":118,"context":"...über ruhige Dörfer und hübsche Häuser. sprach über <mark>diesen<\/mark> uralten Kulturboden, \"wo die Leute noch heute Sachen...","fid":"reading-paginate-2"},{"form":"diesen","weight":"1","pos":490,"context":"...herrlichen Teint gesehen wie seinerzeit  ihre Mutter, und <mark>diesen<\/mark> hat auch die Prinzessin Anne geerbt. Daß...","fid":"reading-paginate-2"}]}]}