{"stem":"feb","instances":[{"docId":"amp-transcript__0006","docUri":"amp-transcript__0006.html","score":1,"contexts":[{"form":"Feb","weight":"1","pos":5,"context":" <mark>Feb<\/mark> 6th, ","fid":"reading-paginate-3"}]},{"docId":"amp-transcript__0004","docUri":"amp-transcript__0004.html","score":1,"contexts":[{"form":"Feb","weight":"1","pos":6,"context":" <mark>Feb<\/mark> 3rd,I966 ","fid":"reading-paginate-3"}]},{"docId":"amp-transcript__0019","docUri":"amp-transcript__0019.html","score":1,"contexts":[{"form":"Feb","weight":"1","pos":5,"context":" <mark>Feb<\/mark> 22nd, 1972 ","fid":"reading-paginate-3"}]}]}