{"stem":"heiraten","instances":[{"docId":"amp-transcript__0047","docUri":"amp-transcript__0047.html","score":1,"contexts":[{"form":"heiraten","weight":"1","pos":332,"context":"..., (In welchen Bars sind sie willkommen? WelchMädchen <mark>heiraten<\/mark> sie?) noch nie war überall Friede auf ihrer...","fid":"text-resize-1"}]},{"docId":"amp-transcript__0039","docUri":"amp-transcript__0039.html","score":1,"contexts":[{"form":"heiraten","weight":"1","pos":398,"context":"...,(In welchen Bars sind sie willkommen? Welche Mdchen <mark>heiraten<\/mark> sie?) ","fid":"text-resize-5"}]}]}