{"stem":"ian","instances":[{"docId":"amp-transcript__0043","docUri":"amp-transcript__0043.html","score":1,"contexts":[{"form":"ian","weight":"1","pos":726,"context":"...Shakepeare,Goethe,Michael Angelo,Tit<mark>ian<\/mark>,Mozart,Beethoven,etc, had never existed...","fid":"reading-paginate-7"}]},{"docId":"amp-transcript__0027","docUri":"amp-transcript__0027.html","score":1,"contexts":[{"form":"ian","weight":"1","pos":495,"context":"...Shakepeare,Goethe,Michael Angelo,Tit<mark>ian<\/mark>,Mozart,Beethoven,etc, had never existed...","fid":"reading-paginate-5"}]}]}