{"stem":"includ","instances":[{"docId":"amp-transcript__0043","docUri":"amp-transcript__0043.html","score":3,"contexts":[{"form":"include","weight":"1","pos":95,"context":"...all artistic fabrication. First,whatever other elements it may <mark>include<\/mark>,the initial impulse to create a secondary world is...","fid":"reading-paginate-3"},{"form":"included","weight":"1","pos":189,"context":"...fantasy. In choosing what objects were to be <mark>included<\/mark>,I was free to select this and reject that,on...","fid":"reading-paginate-3"},{"form":"includ","weight":"1","pos":654,"context":"...orm of political action. Every citizen,poets <mark>includ<\/mark>ed,has a duty to be politically 'engagé', that...","fid":"reading-paginate-7"}]},{"docId":"amp-transcript__0028","docUri":"amp-transcript__0028.html","score":1,"contexts":[{"form":"including","weight":"1","pos":628,"context":"...whether they are O.K. If they are, all rooms, <mark>including<\/mark> my study (which can´t be heated) are open...","fid":"reading-paginate-13"}]},{"docId":"amp-transcript__0009","docUri":"amp-transcript__0009.html","score":1,"contexts":[{"form":"including","weight":"1","pos":16,"context":"...they are O.K. If they are , all rooms, <mark>including<\/mark> my study ( which can't be heated are open...","fid":"reading-paginate-3"}]},{"docId":"amp-transcript__0027","docUri":"amp-transcript__0027.html","score":1,"contexts":[{"form":"includ","weight":"1","pos":423,"context":"...orm of political action. Every citizen,poets <mark>includ<\/mark>ed,has a duty to be politically engagé, that...","fid":"reading-paginate-5"}]}]}