{"stem":"kommen","instances":[{"docId":"amp-transcript__0052","docUri":"amp-transcript__0052.html","score":1,"contexts":[{"form":"kommen","weight":"1","pos":327,"context":"...Musik - , aber ich muss nicht nach Österreich <mark>kommen<\/mark>, um sie zu lesen oder zu höron....","fid":"reading-paginate-5"}]},{"docId":"amp-transcript__0039","docUri":"amp-transcript__0039.html","score":1,"contexts":[{"form":"kommen","weight":"1","pos":186,"context":"...du unvorbereitet auf einen Tag sein solltest,der <mark>kommen<\/mark> musste,eine Zeit, voller Schrecken,...","fid":"reading-paginate-5"}]}]}