{"stem":"love","instances":[{"docId":"amp-transcript__0028","docUri":"amp-transcript__0028.html","score":11,"contexts":[{"form":"Love\"","weight":"1","pos":44,"context":"...Wystan Auden say if he could read \"Auden in <mark>Love\"<\/mark> by Chester´s old college friend and last-...","fid":"reading-paginate-3"},{"form":"Love\"","weight":"1","pos":65,"context":"...recommended holiday  reading. The assessment of \"Auden in <mark>Love\"<\/mark> was a model of compression: \"emetic but compulsive\"...","fid":"reading-paginate-3"},{"form":"loving","weight":"1","pos":142,"context":"..., sensitive and heartless, a man capable of <mark>loving<\/mark> and of being ","fid":"reading-paginate-3"},{"form":"Love","weight":"1","pos":163,"context":"...1977. 2Dorothy J Farnon: Auden in <mark>Love<\/mark>. Simon &amp; Schuster, NY, Faber London 1...","fid":"reading-paginate-3"},{"form":"loved","weight":"1","pos":168,"context":" <mark>loved<\/mark> but who was already - though Auden did not...","fid":"reading-paginate-5"},{"form":"love","weight":"1","pos":257,"context":"...there is evidence in the poetry - sex and <mark>love<\/mark> became, for Auden, two separate matters....","fid":"reading-paginate-5"},{"form":"love","weight":"1","pos":362,"context":"...in the history of English literature. In their <mark>love<\/mark> of music, of opera above all, Kallmanwas...","fid":"reading-paginate-7"},{"form":"Love","weight":"1","pos":668,"context":"...How horrid one is! The U.S. is grim. <mark>Love<\/mark>, Wystan. ","fid":"reading-paginate-13"},{"form":"loving","weight":"1","pos":819,"context":"...that nothing was ever put away, and where his <mark>loving<\/mark> eye saw method, even the least fussy visitor...","fid":"reading-paginate-15"},{"form":"love","weight":"1","pos":1030,"context":"...different things. First of all it is about the <mark>love<\/mark> which every poet, whatever his nationality, has...","fid":"reading-paginate-19"},{"form":"\"Love","weight":"1","pos":1152,"context":"...\"Elegy for Young Lovers\", \"The Bassarids_\" and <mark>\"Love<\/mark>´s Labours Lost\". And together we have made...","fid":"reading-paginate-21"}]},{"docId":"amp-transcript__0038","docUri":"amp-transcript__0038.html","score":3,"contexts":[{"form":"loved","weight":"1","pos":23,"context":"...circs they had to) They buried you like a <mark>loved<\/mark> Old family dog. Categorised enemies Twenty years ago,...","fid":"reading-paginate-3"},{"form":"love","weight":"1","pos":35,"context":"...become good friends, Sharing a common ambit And <mark>love<\/mark> of the word, Over a golden Kremser Had...","fid":"reading-paginate-3"},{"form":"love","weight":"1","pos":251,"context":".... Herewith my effort to do my Gemeindepflicht. <mark>love<\/mark> Wystan. ","fid":"reading-paginate-7"}]},{"docId":"amp-transcript__0002","docUri":"amp-transcript__0002.html","score":1,"contexts":[{"form":"love","weight":"1","pos":60,"context":"...marry?  To what pubs do they go? much <mark>love<\/mark> and best wishes for 1965 Wystan ","fid":"reading-paginate-3"}]},{"docId":"amp-transcript__0042","docUri":"amp-transcript__0042.html","score":1,"contexts":[{"form":"love","weight":"1","pos":39,"context":"...see you, I hope, early in April. <mark>love<\/mark> Wystan ","fid":"reading-paginate-3"}]},{"docId":"amp-transcript__0008","docUri":"amp-transcript__0008.html","score":1,"contexts":[{"form":"love","weight":"1","pos":35,"context":"...W.I. So sorry to be such a nuisance. <mark>love<\/mark> Wystan ","fid":"reading-paginate-3"}]},{"docId":"amp-transcript__0043","docUri":"amp-transcript__0043.html","score":1,"contexts":[{"form":"love","weight":"1","pos":723,"context":"...are as much a part of human experience as <mark>love<\/mark> or nature - but he must never imagine that...","fid":"reading-paginate-7"}]},{"docId":"amp-transcript__0012","docUri":"amp-transcript__0012.html","score":1,"contexts":[{"form":"love","weight":"1","pos":37,"context":"...of my car is W. 618-948. <mark>love<\/mark> Wystan. ","fid":"reading-paginate-3"}]},{"docId":"amp-transcript__0006","docUri":"amp-transcript__0006.html","score":1,"contexts":[{"form":"love","weight":"1","pos":25,"context":".... Will phone you. Do hope you are around· <mark>love<\/mark> Wystan ","fid":"reading-paginate-3"}]},{"docId":"amp-transcript__0010","docUri":"amp-transcript__0010.html","score":1,"contexts":[{"form":"love","weight":"1","pos":11,"context":"...horrid one is ! The U.S. is grim. <mark>love<\/mark> Wystan. ","fid":"reading-paginate-3"}]},{"docId":"amp-transcript__0009","docUri":"amp-transcript__0009.html","score":1,"contexts":[{"form":"love","weight":"1","pos":43,"context":"...that 77 St Mark's Place .N.Y.C. N.Y 10003 . <mark>love<\/mark> Wystan ","fid":"reading-paginate-3"}]},{"docId":"amp-transcript__0011","docUri":"amp-transcript__0011.html","score":1,"contexts":[{"form":"love","weight":"1","pos":39,"context":"...insurance policy) I should be most grateful. <mark>love<\/mark> Wystan. ","fid":"reading-paginate-3"}]},{"docId":"amp-transcript__0017","docUri":"amp-transcript__0017.html","score":1,"contexts":[{"form":"love","weight":"1","pos":19,"context":"...,to pick up any time at your convenience. <mark>love<\/mark> Wystan ","fid":"reading-paginate-3"}]},{"docId":"amp-transcript__0003","docUri":"amp-transcript__0003.html","score":1,"contexts":[{"form":"love","weight":"1","pos":45,"context":"...come or bring it with me next week. <mark>love<\/mark> Wystan ","fid":"reading-paginate-3"}]},{"docId":"amp-transcript__0005","docUri":"amp-transcript__0005.html","score":1,"contexts":[{"form":"love","weight":"1","pos":44,"context":".... The Archbishop came to my first lecture. <mark>love<\/mark> Wystan ","fid":"reading-paginate-3"}]},{"docId":"amp-transcript__0041","docUri":"amp-transcript__0041.html","score":1,"contexts":[{"form":"love","weight":"1","pos":66,"context":"...reaches you. Looking forward to seing you in Sept <mark>love<\/mark> and admiration Wystan ","fid":"reading-paginate-3"}]},{"docId":"amp-transcript__0018","docUri":"amp-transcript__0018.html","score":1,"contexts":[{"form":"love","weight":"1","pos":32,"context":"...Cywydd. Return to New York on NOV 1st. <mark>love<\/mark> Wystan ","fid":"reading-paginate-3"}]},{"docId":"amp-transcript__0007","docUri":"amp-transcript__0007.html","score":1,"contexts":[{"form":"love","weight":"1","pos":31,"context":"..., 24 Russell Square , W.C. I So sorry <mark>love<\/mark> Wystan. ","fid":"reading-paginate-3"}]},{"docId":"amp-transcript__0040","docUri":"amp-transcript__0040.html","score":1,"contexts":[{"form":"love","weight":"1","pos":11,"context":"...will be fine. Shall look forward to it. <mark>love<\/mark> Wystan ","fid":"reading-paginate-3"}]},{"docId":"amp-transcript__0004","docUri":"amp-transcript__0004.html","score":1,"contexts":[{"form":"love","weight":"1","pos":130,"context":"...to get back to Kirchstetten about April 20th. much <mark>love<\/mark> and greetings to son and mum-in-law Wystan...","fid":"reading-paginate-3"}]},{"docId":"amp-transcript__0016","docUri":"amp-transcript__0016.html","score":1,"contexts":[{"form":"love","weight":"1","pos":21,"context":"...and your mother come to lunch  next Tuesday ? <mark>love<\/mark> Wystan ","fid":"reading-paginate-3"}]},{"docId":"amp-transcript__0014","docUri":"amp-transcript__0014.html","score":1,"contexts":[{"form":"love","weight":"1","pos":25,"context":"...both.  Longing to hear about the Royal vsit. <mark>love<\/mark> Wystan' ","fid":"reading-paginate-3"}]},{"docId":"amp-transcript__0020","docUri":"amp-transcript__0020.html","score":1,"contexts":[{"form":"love","weight":"1","pos":27,"context":"...booked a room at the Hotel hof Altburgenhof, <mark>love<\/mark> Wystan. ","fid":"reading-paginate-3"}]},{"docId":"amp-transcript__0019","docUri":"amp-transcript__0019.html","score":1,"contexts":[{"form":"love","weight":"1","pos":17,"context":"...my winters in Oxford not in New York. <mark>love<\/mark> Wystan ","fid":"reading-paginate-3"}]},{"docId":"amp-transcript__0013","docUri":"amp-transcript__0013.html","score":1,"contexts":[{"form":"love","weight":"1","pos":49,"context":"...get intouch with the Insurance till I know more <mark>love<\/mark> Wystan. ","fid":"reading-paginate-3"}]},{"docId":"amp-transcript__0023","docUri":"amp-transcript__0023.html","score":1,"contexts":[{"form":"love","weight":"1","pos":13,"context":"...and where are you? If in Fridau,we would <mark>love<\/mark> to see you. Am expecting Christiane Zimmer here about...","fid":"reading-paginate-3"}]},{"docId":"amp-transcript__0022","docUri":"amp-transcript__0022.html","score":1,"contexts":[{"form":"love","weight":"1","pos":15,"context":"...Delighted to hear you are back and would <mark>love<\/mark> to see you anytime: Are you living in...","fid":"reading-paginate-3"}]},{"docId":"amp-transcript__0015","docUri":"amp-transcript__0015.html","score":1,"contexts":[{"form":"love","weight":"1","pos":29,"context":"...you will be returning to Vienna from Fridau. <mark>love<\/mark> and again thanks ever so much Wystan ","fid":"reading-paginate-3"}]},{"docId":"amp-transcript__0027","docUri":"amp-transcript__0027.html","score":1,"contexts":[{"form":"love","weight":"1","pos":478,"context":"...are as much a part of human experience as <mark>love<\/mark> or nature - but he must never imagine that...","fid":"reading-paginate-5"}]},{"docId":"amp-transcript__0001","docUri":"amp-transcript__0001.html","score":1,"contexts":[{"form":"love","weight":"1","pos":31,"context":"...Florence,but I expect him back on Tuesday. <mark>love<\/mark> Wystan ","fid":"reading-paginate-3"}]},{"docId":"amp-transcript__0052","docUri":"amp-transcript__0052.html","score":1,"contexts":[{"form":"'Love's","weight":"1","pos":481,"context":"..., 'Elegy for Young Lovers', 'The Bassarids' und <mark>'Love's<\/mark> Labours Lost'. ('Weg eines Wüstlings',...","fid":"reading-paginate-7"}]}]}