{"stem":"mutter","instances":[{"docId":"amp-transcript__0053","docUri":"amp-transcript__0053.html","score":2,"contexts":[{"form":"Mutter","weight":"1","pos":795,"context":"...zum T. Besuch draussen, u.a. Sony, ihre <mark>Mutter<\/mark> und die Amélie. Marko und ich sind Samstag...","fid":"text-resize-2"},{"form":"Mutter","weight":"1","pos":945,"context":"...mit einem so herrlichen Teint gesehen wie seinerzeit ihre <mark>Mutter<\/mark>, und diesen hat auch die Prinzessin Anne geerbt...","fid":"text-resize-2"}]},{"docId":"amp-transcript__0028","docUri":"amp-transcript__0028.html","score":1,"contexts":[{"form":"muttering","weight":"1","pos":1371,"context":"...already lay far behind, the car radio went on <mark>muttering<\/mark> to itself unheeded until the familiar voice of Friedrich...","fid":"text-resize-23"}]}]}