{"stem":"profound","instances":[{"docId":"amp-transcript__0043","docUri":"amp-transcript__0043.html","score":2,"contexts":[{"form":"profound","weight":"1","pos":303,"context":"...for oneself alone and writing poetry,there is,of course,a <mark>profound<\/mark> difference. A fantasy world exists only in the...","fid":"text-resize-5"},{"form":"profound","weight":"1","pos":484,"context":"...he cannot 'rebel' against the past without having a <mark>profound<\/mark> reverence for it. ","fid":"text-resize-5"}]},{"docId":"amp-transcript__0027","docUri":"amp-transcript__0027.html","score":2,"contexts":[{"form":"profound","weight":"1","pos":305,"context":"...or oneself alone and writing poetry,there is,of course,a <mark>profound<\/mark> difference. A fantasy world exists only in the...","fid":"text-resize-3"},{"form":"profound","weight":"1","pos":502,"context":"...he cannot 'reel' against the pst without having a <mark>profound<\/mark> reverence for it. ","fid":"text-resize-3"}]}]}