{"stem":"schauen","instances":[{"docId":"amp-transcript__0047","docUri":"amp-transcript__0047.html","score":1,"contexts":[{"form":"schauen","weight":"1","pos":31,"context":"...z bleiben und durch den Zaun deines Gartens zu <mark>schauen<\/mark>, in dem man dich (die Umstände verlangten...","fid":"text-resize-1"}]},{"docId":"amp-transcript__0053","docUri":"amp-transcript__0053.html","score":1,"contexts":[{"form":"schauen","weight":"1","pos":855,"context":"...Jetzt will ich Deine Fragen beantworten und sonst noch <mark>schauen<\/mark> was in Deinem letzten Brief steht. Die grande...","fid":"text-resize-2"}]},{"docId":"amp-transcript__0039","docUri":"amp-transcript__0039.html","score":1,"contexts":[{"form":"schauen","weight":"1","pos":106,"context":"...zu bleiben und durch den Zaun deines Gartens zu <mark>schauen<\/mark>,in dem🗴 dich(die Umstnde verlangten es)...","fid":"text-resize-5"}]}]}