{"stem":"schon","instances":[{"docId":"amp-transcript__0047","docUri":"amp-transcript__0047.html","score":2,"contexts":[{"form":"Schon","weight":"1","pos":248,"context":"...dem annus mirabilis als die Parität gestürzt wurde. <mark>Schon<\/mark> waren die Reiche, die verloren hatten, genügend...","fid":"text-resize-1"},{"form":"schon","weight":"1","pos":298,"context":"...wir bei Hochzeiten, bei denen Braut und Bräutigam <mark>schon<\/mark> auf der Welt waren als sich der Schatten gehoben...","fid":"text-resize-1"}]},{"docId":"amp-transcript__0053","docUri":"amp-transcript__0053.html","score":2,"contexts":[{"form":"schon","weight":"1","pos":4,"context":" Ich habe <mark>schon<\/mark> sehr lange nicht geschrieben, Du wirst Dich,...","fid":"text-resize-1"},{"form":"schon","weight":"1","pos":13,"context":"...geschrieben, Du wirst Dich, fürchte ich, <mark>schon<\/mark> kränken. Sehr schön war es, Deine Stimme zu...","fid":"text-resize-1"}]}]}