{"stem":"servic","instances":[{"docId":"amp-transcript__0031","docUri":"amp-transcript__0031.html","score":3,"contexts":[{"form":"service","weight":"1","pos":284,"context":"...name and address of the clergyman who took the <mark>service<\/mark> with the RC pasrish priest and I wrote to...","fid":"text-resize-3"},{"form":"service","weight":"1","pos":290,"context":"...to find out´whether he can remember the form of <mark>service<\/mark> etc. but no answer so far. This would be...","fid":"text-resize-3"},{"form":"service","weight":"1","pos":296,"context":"...because though common practice in England such an ecumenical <mark>service<\/mark> was a novelty here and caused much comment....","fid":"text-resize-3"}]},{"docId":"amp-transcript__0030","docUri":"amp-transcript__0030.html","score":3,"contexts":[{"form":"service","weight":"1","pos":47,"context":"...kind as to confirm that you took the ecumenical <mark>service<\/mark> - shall Iscall it that? in the church at...","fid":"text-resize-1"},{"form":"service","weight":"1","pos":58,"context":"...parish priest? Do you recall the form of <mark>service<\/mark> used, and did John Auden consult you about it?...","fid":"text-resize-1"},{"form":"service","weight":"1","pos":73,"context":"...the right bell. Then there was the burial <mark>service<\/mark>. I am told that the whole occasion aroused...","fid":"text-resize-1"}]},{"docId":"amp-transcript__0028","docUri":"amp-transcript__0028.html","score":3,"contexts":[{"form":"service","weight":"1","pos":1744,"context":"...Much; there was also the matter of the church <mark>service<\/mark> and the prayers at the graveside. Many people...","fid":"text-resize-29"},{"form":"service","weight":"1","pos":1793,"context":"...and ask him to officiate. What form of <mark>service<\/mark> this should be - there could be no question...","fid":"text-resize-29"},{"form":"service","weight":"1","pos":1906,"context":".... To British ears quite unremarkable, the ecumenical <mark>service<\/mark> was much taIked about in Austrian circles because nothing...","fid":"text-resize-31"}]}]}