{"stem":"sunday","instances":[{"docId":"amp-transcript__0028","docUri":"amp-transcript__0028.html","score":2,"contexts":[{"form":"Sunday","weight":"1","pos":56,"context":"...stepmother Dorothy J. Farnon?2 In July 1985 the <mark>Sunday<\/mark> Times published a list of recommended holiday  reading....","fid":"reading-paginate-3"},{"form":"Sunday","weight":"1","pos":1302,"context":"...to tea the next day? That was the <mark>Sunday<\/mark>. ","fid":"reading-paginate-23"}]},{"docId":"amp-transcript__0042","docUri":"amp-transcript__0042.html","score":1,"contexts":[{"form":"Sunday","weight":"1","pos":30,"context":" Dear Stella, Terribly sorry about last <mark>Sunday<\/mark>. Since I had no idea when we should...","fid":"reading-paginate-3"}]},{"docId":"amp-transcript__0007","docUri":"amp-transcript__0007.html","score":1,"contexts":[{"form":"Sunday","weight":"1","pos":13,"context":" <mark>Sunday<\/mark>. ","fid":"reading-paginate-3"}]},{"docId":"amp-transcript__0022","docUri":"amp-transcript__0022.html","score":1,"contexts":[{"form":"Sunday","weight":"1","pos":24,"context":"....? I read your piece in Die Presse last <mark>Sunday<\/mark> with great interest, yours ever Wystan ","fid":"reading-paginate-3"}]},{"docId":"amp-transcript__0001","docUri":"amp-transcript__0001.html","score":1,"contexts":[{"form":"Sunday","weight":"1","pos":6,"context":"<mark>Sunday<\/mark>.","fid":"reading-paginate-3"}]}]}