{"stem":"term","instances":[{"docId":"amp-transcript__0028","docUri":"amp-transcript__0028.html","score":2,"contexts":[{"form":"term","weight":"1","pos":513,"context":"...the same, have been easy living on a long-<mark>term<\/mark> basis with Auden in New Yowk while attempting...","fid":"reading-paginate-9"},{"form":"term","weight":"1","pos":773,"context":"...in the Austrians calledd them \"American\" - the <mark>term<\/mark> is now as extinct as \"Russian\" tea but...","fid":"reading-paginate-15"}]}]}