{"stem":"territori","instances":[{"docId":"amp-transcript__0043","docUri":"amp-transcript__0043.html","score":1,"contexts":[{"form":"territory","weight":"1","pos":364,"context":"...members of their species vital information about food,<mark>territory<\/mark>,sex, the presence of enemies etc,and in...","fid":"text-resize-5"}]},{"docId":"amp-transcript__0027","docUri":"amp-transcript__0027.html","score":1,"contexts":[{"form":"territory","weight":"1","pos":366,"context":"...members of their species vital information about food,<mark>territory<\/mark>,sex, the presence of enemies,etc,and in...","fid":"text-resize-3"}]},{"docId":"amp-transcript__0029","docUri":"amp-transcript__0029.html","score":1,"contexts":[{"form":"territorial","weight":"1","pos":24,"context":"...to blame for the Pueblo affair &amp; s in <mark>territorial<\/mark> waters. may have to vote Repulican gh he's...","fid":"text-resize-1"}]}]}