{"stem":"told","instances":[{"docId":"amp-transcript__0028","docUri":"amp-transcript__0028.html","score":6,"contexts":[{"form":"told","weight":"1","pos":221,"context":"...heir way home in my car. When Chester <mark>told<\/mark> me later on that the man who, as...","fid":"reading-paginate-5"},{"form":"told","weight":"1","pos":332,"context":"...had a full work programme, and when he <mark>told<\/mark> me he could hardly think how Chester would get...","fid":"reading-paginate-7"},{"form":"told","weight":"1","pos":684,"context":"...as stamps or cigarettes. \"Life\" magazine, he <mark>told<\/mark> me one day with a beaming smile, had...","fid":"reading-paginate-13"},{"form":"told","weight":"1","pos":734,"context":"...them to send a few bottles out - he <mark>told<\/mark> me the brand name - that would be splendid...","fid":"reading-paginate-15"},{"form":"told","weight":"1","pos":1697,"context":"...everyone had agreed that Auden´s relations must be <mark>told<\/mark> immediately that the funeral had been postponed, the...","fid":"reading-paginate-29"},{"form":"told","weight":"1","pos":1847,"context":"...concentrating mill is Vereinigungsmühle.\" \"What a mercy you´ve <mark>told<\/mark> me\" I said, relieved. \"I should have to...","fid":"reading-paginate-31"}]}]}